pymhelper/__init__.py
pymhelper/dataclasseshelper.py
pymhelper/files.py
pymhelper/numbers.py
pymhelper/assets/__init__.py
pymhelper/assets/base.py
pymhelper/assets/datamodels.py
pymhelper/assets/exceptions.py
pymhelper/klines/__init__.py
pymhelper/klines/base.py
pymhelper/klines/datamodels.py
pymhelper/orders/__init__.py
pymhelper/orders/datamodels.py
pymhelper-0.1.5.dist-info/LICENSE
pymhelper-0.1.5.dist-info/METADATA
pymhelper-0.1.5.dist-info/WHEEL
pymhelper-0.1.5.dist-info/top_level.txt
pymhelper-0.1.5.dist-info/RECORD
